README.md
setup.py
moncon/__init__.py
moncon/moncon.py
moncon.egg-info/PKG-INFO
moncon.egg-info/SOURCES.txt
moncon.egg-info/dependency_links.txt
moncon.egg-info/requires.txt
moncon.egg-info/top_level.txt
scripts/moncon