Metadata-Version: 1.0
Name: moncon
Version: 0.0.1
Summary: Simple CLI wrapper for some common Monyog REST API commands.
Home-page: https://github.com/rcbensley/moncon/
Author: UNKNOWN
Author-email: UNKNOWN
License: UNKNOWN
Keywords: monyog
Platform: UNKNOWN
